ut_xls/__init__.py
ut_xls/__version__.py
ut_xls/dec.py
ut_xls/py.typed
ut_xls/op/__init__.py
ut_xls/op/iocwb.py
ut_xls/op/pathioiwb.py
ut_xls/op/pathioiws.py
ut_xls/op/pathioowb.py
ut_xls/op/pathiouwb.py
ut_xls/op/pathkioiwb.py
ut_xls/op/pathkioowb.py
ut_xls/op/rw.py
ut_xls/op/wb.py
ut_xls/op/ws.py
ut_xls/pd/__init__.py
ut_xls/pd/pathioiwb.py
ut_xls/pd/pathioowb.py
ut_xls/pd/pathkioiwb.py
ut_xls/pe/__init__.py
ut_xls/pe/iocwb.py
ut_xls/pe/pathioowb.py
ut_xls/pe/pathkioowb.py
ut_xls/pl/__init__.py
ut_xls/pl/pathioiwb.py
ut_xls-2.0.0.20251021.dist-info/licenses/LICENSE.txt
ut_xls-2.0.0.20251021.dist-info/METADATA
ut_xls-2.0.0.20251021.dist-info/WHEEL
ut_xls-2.0.0.20251021.dist-info/top_level.txt
ut_xls-2.0.0.20251021.dist-info/RECORD
