Metadata-Version: 2.4
Name: ut_xls
Version: 2.0.0.20251021
Summary: Utilities for Excel files.
Author-email: Bernd Stroehle <bernd.stroehle@bs29.com>
Maintainer-email: Bernd Stroehle <bernd.stroehle@bs29.com>
License-Expression: GPL-3.0-only WITH Classpath-exception-2.0 OR BSD-3-Clause
Project-URL: Source Code, https://github.com/bs29/ut_xls/tree/master
Project-URL: Homepage, https://kosakya.de/
Project-URL: Documentation, https://ut_xls-apc.readthedocs.io/en/latest
Project-URL: Apache-2.0 License, https://apache.org/licenses/LICENSE-2.0
Project-URL: GPLv3 License, https://www.gnu.org/licenses/gpl-3.0.en.html
Classifier: Development Status :: 5 - Production/Stable
Classifier: Intended Audience :: Developers
Classifier: Operating System :: OS Independent
Classifier: Programming Language :: Python :: 3.12
Classifier: Natural Language :: English
Classifier: Topic :: Software Development :: Libraries :: Python Modules
Requires-Python: >=3.10
License-File: LICENSE.txt
Requires-Dist: openpyxl>=3.1.5
Requires-Dist: pandas>=2.3.3
Requires-Dist: polars>=1.34.0
Requires-Dist: PyExcelerate>=0.12.0
Requires-Dist: ut_aod>=1.4.5.20251009
Requires-Dist: ut_arr>=1.3.8.20251001
Requires-Dist: ut_dfr>=1.1.1.20250915
Requires-Dist: ut_dic>=1.5.5.20251011
Requires-Dist: ut_log>=1.3.4.20251009
Requires-Dist: ut_obj>=1.2.3.20251009
Requires-Dist: ut_path>=1.4.0.20251012
Dynamic: license-file
